{
  "prec-invest-credit": {
    "seenIds": [
      "603521",
      "603719",
      "332324",
      "423914",
      "344522",
      "349950",
      "342812",
      "424102",
      "608443",
      "424104"
    ],
    "lastCheckedAt": "2026-07-18T23:40:34+09:00"
  },
  "prec-employ-credit": {
    "seenIds": [
      "603521",
      "343090",
      "603719",
      "332324",
      "343994",
      "304526",
      "344522",
      "342812",
      "616293",
      "303028"
    ],
    "lastCheckedAt": "2026-07-18T23:40:34+09:00"
  },
  "prec-rnd-credit": {
    "seenIds": [
      "616291",
      "613925",
      "616995",
      "616937",
      "607117",
      "620331",
      "615547",
      "606281",
      "620251",
      "613871"
    ],
    "lastCheckedAt": "2026-07-18T23:40:34+09:00"
  },
  "prec-startup": {
    "seenIds": [
      "614767",
      "499267",
      "616745",
      "242413",
      "617459",
      "606529",
      "608297",
      "242409",
      "620011",
      "608295"
    ],
    "lastCheckedAt": "2026-07-18T23:40:34+09:00"
  },
  "prec-sme-credit": {
    "seenIds": [
      "349884",
      "347160",
      "614845",
      "609109",
      "616993",
      "348240",
      "337844",
      "607125",
      "337024",
      "618591"
    ],
    "lastCheckedAt": "2026-07-18T23:40:34+09:00"
  },
  "prec-honest-report": {
    "seenIds": [
      "337910",
      "423740",
      "335700",
      "617741",
      "343950",
      "330416",
      "336766",
      "345838",
      "423738",
      "423746"
    ],
    "lastCheckedAt": "2026-07-18T23:40:34+09:00"
  },
  "prec-foreign-credit": {
    "seenIds": [
      "622015",
      "620263",
      "499593",
      "616263",
      "620261",
      "617521",
      "620201",
      "621889",
      "619627",
      "618001"
    ],
    "lastCheckedAt": "2026-07-18T23:40:34+09:00"
  },
  "prec-bad-debt": {
    "seenIds": [
      "318134",
      "273922",
      "310114",
      "322678",
      "319850"
    ],
    "lastCheckedAt": "2026-07-18T23:40:34+09:00"
  },
  "prec-disabled-levy": {
    "seenIds": [
      "207149",
      "349342",
      "121025",
      "207122",
      "130691",
      "145147",
      "612379",
      "617669",
      "612375",
      "147000"
    ],
    "lastCheckedAt": "2026-07-18T23:40:34+09:00"
  },
  "prec-interest-nondeductible": {
    "seenIds": [
      "351202",
      "300184",
      "241404",
      "606313",
      "213824",
      "605151",
      "620147",
      "321924",
      "605327",
      "612611"
    ],
    "lastCheckedAt": "2026-07-18T23:40:34+09:00"
  },
  "prec-provisional-payment": {
    "seenIds": [
      "418750",
      "621313",
      "606313",
      "242189",
      "418718",
      "417518",
      "342984",
      "345180",
      "335716",
      "612611"
    ],
    "lastCheckedAt": "2026-07-18T23:40:34+09:00"
  },
  "prec-bad-debt-reserve": {
    "seenIds": [
      "300752",
      "252354",
      "248378",
      "321790",
      "615169"
    ],
    "lastCheckedAt": "2026-07-18T23:40:34+09:00"
  },
  "prec-donation-nondeductible": {
    "seenIds": [
      "259590",
      "243397"
    ],
    "lastCheckedAt": "2026-07-18T23:40:34+09:00"
  },
  "prec-entertainment": {
    "seenIds": [
      "606597",
      "332798",
      "345110",
      "344086",
      "343906",
      "617429",
      "615491",
      "342822",
      "332910",
      "617729"
    ],
    "lastCheckedAt": "2026-07-18T23:40:34+09:00"
  },
  "prec-company-car": {
    "seenIds": [
      "332940",
      "337284",
      "302800",
      "355798",
      "260832",
      "351562",
      "302488",
      "290108"
    ],
    "lastCheckedAt": "2026-07-18T23:40:34+09:00"
  },
  "prec-excessive-expense": {
    "seenIds": [
      "296312"
    ],
    "lastCheckedAt": "2026-07-18T23:40:34+09:00"
  },
  "prec-asset-loss": {
    "seenIds": [
      "303814",
      "294094",
      "227070",
      "230028",
      "320702",
      "332044"
    ],
    "lastCheckedAt": "2026-07-18T23:40:34+09:00"
  },
  "prec-depreciation": {
    "seenIds": [
      "346206",
      "350540",
      "345958",
      "348986",
      "325282",
      "608815",
      "621243",
      "347840",
      "324580",
      "334218"
    ],
    "lastCheckedAt": "2026-07-18T23:40:34+09:00"
  },
  "prec-input-vat-denial": {
    "seenIds": [
      "605435",
      "613643",
      "619099",
      "619951",
      "613377",
      "612597",
      "606683",
      "619791",
      "418068",
      "607861"
    ],
    "lastCheckedAt": "2026-07-18T23:40:34+09:00"
  },
  "prec-wrongful-calc": {
    "seenIds": [
      "621031",
      "618097",
      "612659",
      "616383",
      "615171",
      "614973",
      "616265",
      "617905",
      "618041",
      "617117"
    ],
    "lastCheckedAt": "2026-07-18T23:40:34+09:00"
  }
}
